sertit/__init__.py
sertit/__meta__.py
sertit/arcpy.py
sertit/ci.py
sertit/dask.py
sertit/display.py
sertit/exception.py
sertit/files.py
sertit/geometry.py
sertit/logs.py
sertit/misc.py
sertit/network.py
sertit/os_utils.py
sertit/path.py
sertit/perf.py
sertit/rasters.py
sertit/rasters_rio.py
sertit/s3.py
sertit/snap.py
sertit/strings.py
sertit/types.py
sertit/unistra.py
sertit/vectors.py
sertit/xml.py
sertit-1.50.1.dist-info/licenses/LICENSE
sertit-1.50.1.dist-info/licenses/NOTICE
sertit-1.50.1.dist-info/METADATA
sertit-1.50.1.dist-info/WHEEL
sertit-1.50.1.dist-info/top_level.txt
sertit-1.50.1.dist-info/RECORD
