Metadata-Version: 2.4
Name: sertit
Version: 1.50.1
Summary: SERTIT python library for generic tools
Author-email: ICube-SERTIT <dev-sertit@unistra.fr>
License: Apache 2.0
Project-URL: Bug_Tracker, https://github.com/sertit/sertit-utils/issues
Project-URL: Documentation, https://sertit-utils.readthedocs.io/latest/
Project-URL: Source_Code, https://github.com/sertit/sertit-utils
Classifier: Development Status :: 5 - Production/Stable
Classifier: Intended Audience :: Developers
Classifier: Intended Audience :: Science/Research
Classifier: Natural Language :: English
Classifier: License :: OSI Approved :: Apache Software License
Classifier: Programming Language :: Python :: 3
Classifier: Programming Language :: Python :: 3.10
Classifier: Programming Language :: Python :: 3.11
Classifier: Programming Language :: Python :: 3.12
Classifier: Programming Language :: Python :: 3.13
Classifier: Programming Language :: Python :: 3.14
Classifier: Operating System :: OS Independent
Classifier: Topic :: Scientific/Engineering :: GIS
Classifier: Topic :: Software Development :: Libraries :: Python Modules
Requires-Python: >=3.10
License-File: LICENSE
License-File: NOTICE
Requires-Dist: semver
Requires-Dist: tqdm
Requires-Dist: lxml
Requires-Dist: dill
Requires-Dist: psutil
Requires-Dist: geopandas>=0.14.4
Requires-Dist: cloudpathlib[s3]>=0.15.0
Requires-Dist: xarray>=2024.06.0
Provides-Extra: colorlog
Requires-Dist: colorlog; extra == "colorlog"
Provides-Extra: rasters-rio
Requires-Dist: rasterio>=1.3.10; extra == "rasters-rio"
Provides-Extra: rasters
Requires-Dist: sertit[rasters_rio]; extra == "rasters"
Requires-Dist: rioxarray>=0.15.0; extra == "rasters"
Requires-Dist: xdem; extra == "rasters"
Provides-Extra: nearest-neighbors
Requires-Dist: scikit-learn>=1.4.2; extra == "nearest-neighbors"
Provides-Extra: dask
Requires-Dist: sertit[rasters]; extra == "dask"
Requires-Dist: dask[distributed]>=2024.5.1; extra == "dask"
Requires-Dist: s3fs; extra == "dask"
Requires-Dist: odc-geo[tiff]>=0.5.0; extra == "dask"
Requires-Dist: xarray-spatial>=0.3.6; extra == "dask"
Provides-Extra: full
Requires-Dist: sertit[colorlog,dask,nearest_neighbors]; extra == "full"
Dynamic: license-file
